weatherapp/__init__.py
weatherapp/weather.py
githubusername_weatherapp_11_2024-0.1.dist-info/METADATA
githubusername_weatherapp_11_2024-0.1.dist-info/WHEEL
githubusername_weatherapp_11_2024-0.1.dist-info/top_level.txt
githubusername_weatherapp_11_2024-0.1.dist-info/RECORD
