Metadata-Version: 2.1
Name: githubusername-weatherapp-11-2024
Version: 0.1
Summary: Une application simple pour obtenir des données météo d'une ville
Home-page: https://github.com/githubusername/WeatherApp
Author: Votre Nom
Author-email: votre.email@example.com
License: UNKNOWN
Platform: UNKNOWN
Classifier: Programming Language :: Python :: 3
Classifier: License :: OSI Approved :: MIT License
Classifier: Operating System :: OS Independent
Requires-Python: >=3.6
Requires-Dist: requests
